{"companies":[{"icon":"http://d3pw3vmjej36h2.cloudfront.net/company/logo/resize/460/115/70/logo.png?v=3.996","page":"http://gamineazy-entertainment.yspages.com","name":"Gamineazy Entertainment"},{"icon":"http://d3pw3vmjej36h2.cloudfront.net/company/logo/resize/6242/115/70/logo.png?v=3.996","page":"http://iplpoll.yspages.com","name":"IPLPOLL"},{"icon":"http://d3pw3vmjej36h2.cloudfront.net/company/logo/resize/7621/115/70/logo.png?v=3.996","page":"http://play-games24x7.yspages.com","name":"Play Games24x7"},{"icon":"http://d3pw3vmjej36h2.cloudfront.net/company/logo/resize/190/115/70/logo.png?v=3.996","page":"http://hashcube.yspages.com","name":"HashCube"},{"icon":"http://d3pw3vmjej36h2.cloudfront.net/company/logo/resize/5246/115/70/logo.png?v=3.996","page":"http://indyarocks.yspages.com","name":"Indyarocks"},{"icon":"http://d3pw3vmjej36h2.cloudfront.net/company/logo/resize/5266/115/70/logo.png?v=3.996","page":"http://toufee.yspages.com","name":"Toufee"},{"icon":"http://d3pw3vmjej36h2.cloudfront.net/company/logo/resize/4783/115/70/logo.png?v=3.996","page":"http://games2win.yspages.com","name":"Games2Win"},{"icon":"http://d3pw3vmjej36h2.cloudfront.net/company/logo/resize/4724/115/70/logo.png?v=3.996","page":"http://bash-gaming.yspages.com","name":"Bash Gaming"},{"icon":"http://d3pw3vmjej36h2.cloudfront.net/company/logo/resize/5270/115/70/logo.png?v=3.996","page":"http://medianama.yspages.com","name":"MediaNama"},{"icon":"http://d3pw3vmjej36h2.cloudfront.net/company/logo/resize/5293/90/35/logo.png?v=3.996","page":"http://istrike.yspages.com","name":"Istrike"},{"icon":"http://d3pw3vmjej36h2.cloudfront.net/company/logo/resize/4080/90/35/logo.png?v=3.996","page":"http://gamewallah.yspages.com","name":"GameWallah"},{"icon":"http://d3pw3vmjej36h2.cloudfront.net/company/logo/resize/5296/90/35/logo.png?v=3.996","page":"http://46-idea-street.yspages.com","name":"46 Idea Street"},{"icon":"http://d3pw3vmjej36h2.cloudfront.net/company/logo/resize/1895/90/35/logo.png?v=3.996","page":"http://mega-mentis-infotech.yspages.com","name":"Mega Mentis Infotech"},{"icon":"http://d3pw3vmjej36h2.cloudfront.net/company/logo/resize/5574/90/35/logo.png?v=3.996","page":"http://titip.yspages.com","name":"Titip"},{"icon":"http://d3pw3vmjej36h2.cloudfront.net/company/logo/resize/954/90/35/logo.png?v=3.996","page":"http://rhythm-labs.yspages.com","name":"Rhythm Labs"},{"icon":"http://d3pw3vmjej36h2.cloudfront.net/company/logo/resize/1221/90/35/logo.png?v=3.996","page":"http://nextwave-multimedia-pvt-ltd.yspages.com","name":"Nextwave Multimedia Pvt Ltd"},{"icon":"http://d3pw3vmjej36h2.cloudfront.net/company/logo/resize/5595/90/35/logo.png?v=3.996","page":"http://paxplay.yspages.com","name":"PaxPlay"},{"icon":"http://d3pw3vmjej36h2.cloudfront.net/company/logo/resize/141/90/35/logo.png?v=3.996","page":"http://the-awesome-game-studio-tags.yspages.com","name":"The Awesome Game Studio (TAGS)"},{"icon":"http://d3pw3vmjej36h2.cloudfront.net/company/logo/resize/1172/90/35/logo.png?v=3.996","page":"http://coffin-games.yspages.com","name":"Coffin Games"},{"icon":"http://d3pw3vmjej36h2.cloudfront.net/company/logo/resize/1843/90/35/logo.png?v=3.996","page":"http://funstar-studios.yspages.com","name":"Funstar Studios"},{"icon":"http://d3pw3vmjej36h2.cloudfront.net/company/logo/resize/1000/90/35/logo.png?v=3.996","page":"http://rolocule-games.yspages.com","name":"Rolocule Games"},{"icon":"http://d3pw3vmjej36h2.cloudfront.net/company/logo/resize/211/90/35/logo.png?v=3.996","page":"http://gamesrnd.yspages.com","name":"GamesRnD"},{"icon":"http://d3pw3vmjej36h2.cloudfront.net/company/logo/resize/0/90/35/logo.png?v=3.996","page":"http://funvoltage.yspages.com","name":"FunVoltage"},{"icon":"http://d3pw3vmjej36h2.cloudfront.net/company/logo/resize/8238/90/35/logo.png?v=3.996","page":"http://artillery.yspages.com","name":"Artillery"},{"icon":"http://d3pw3vmjej36h2.cloudfront.net/company/logo/resize/9539/90/35/logo.png?v=3.996","page":"http://junglee-rummy.yspages.com","name":"Junglee Rummy"}],"number":25}
